{
  "room_rect-web.glb": {
    "pos": {
      "x": 0,
      "y": 1.2,
      "z": 0
    },
    "rot": {
      "x": 0,
      "y": 0,
      "z": 0
    },
    "scale": {
      "x": 0.8,
      "y": 2,
      "z": 0.8
    }
  },
  "room_spire-web.glb": {
    "pos": {
      "x": 0,
      "y": 2.6,
      "z": 0
    },
    "rot": {
      "x": 0,
      "y": 0,
      "z": 0
    },
    "scale": {
      "x": 3.7,
      "y": 4.9,
      "z": 3.7
    }
  },
  "room_secret-web.glb": {
    "pos": {
      "x": 0,
      "y": 1.25,
      "z": 0
    },
    "rot": {
      "x": 0,
      "y": 0,
      "z": 0
    },
    "scale": {
      "x": 1.1,
      "y": 1.1,
      "z": 1.1
    }
  },
  "waypoint-web.glb": {
    "pos": {
      "x": 0,
      "y": 0.1,
      "z": 0
    },
    "rot": {
      "x": 0,
      "y": 0,
      "z": 0
    },
    "scale": {
      "x": 0.3,
      "y": 0.5,
      "z": 0.3
    }
  },
  "room_round-web.glb": {
    "pos": {
      "x": 0,
      "y": 0.85,
      "z": 0
    },
    "rot": {
      "x": 0,
      "y": 0,
      "z": 0
    },
    "scale": {
      "x": 1,
      "y": 2.1,
      "z": 1
    }
  },
  "room_dome-web.glb": {
    "pos": {
      "x": 0,
      "y": 0.55,
      "z": 0
    },
    "rot": {
      "x": 0,
      "y": 0,
      "z": 0
    },
    "scale": {
      "x": 1,
      "y": 1,
      "z": 1
    }
  },
  "campfire_tower-web.glb": {
    "pos": {
      "x": 0,
      "y": 0.6,
      "z": 0
    },
    "rot": {
      "x": 0,
      "y": 0,
      "z": 0
    },
    "scale": {
      "x": 1,
      "y": 1,
      "z": 1
    }
  }
}
